{"cameraMode":{"drawMode":0,"name":"Shaded","section":"Shading Mode"},"sceneLighting":false,"audioPlay":false,"sceneViewState":{"m_AlwaysRefresh":false,"showFog":true,"showSkybox":true,"showFlares":true,"showImageEffects":true,"showParticleSystems":true,"showVisualEffectGraphs":true,"m_FxEnabled":true},"in2DMode":false,"pivot":{"x":7.908142566680908,"y":-3.280027389526367,"z":7.528586387634277},"rotation":{"x":-0.13072744011878968,"y":0.755159854888916,"z":0.15859097242355348,"w":0.6224938631057739},"size":0.29438698291778567,"orthographic":false}